gaussianlda/__init__.py
gaussianlda/model.py
gaussianlda/mp_utils.py
gaussianlda/perplexity.py
gaussianlda/prior.py
gaussianlda/utils.py
gaussianlda/trainer/__init__.py
gaussianlda/trainer/_chol_alias_fast_sample.py
gaussianlda/trainer/_old_alias.py
gaussianlda/trainer/chol.py
gaussianlda/trainer/chol_alias.py
gaussianlda/trainer/test_vose.py
gaussianlda-0.2.14.dist-info/LICENSE.txt
gaussianlda-0.2.14.dist-info/METADATA
gaussianlda-0.2.14.dist-info/WHEEL
gaussianlda-0.2.14.dist-info/top_level.txt
gaussianlda-0.2.14.dist-info/RECORD
