Metadata-Version: 2.1
Name: gaussianlda
Version: 0.2.14
Summary: Implementation of Gaussian LDA topic model, with efficiency tricks
Home-page: https://github.com/markgw/gaussianlda
Author: Mark Granroth-Wilding
License: UNKNOWN
Project-URL: Based on, https://github.com/rajarshd/Gaussian_LDA
Project-URL: Funding, https://www.newseye.eu/
Keywords: gaussian lda topic-model machine-learning
Platform: UNKNOWN
Classifier: Development Status :: 4 - Beta
Classifier: Intended Audience :: Developers
Classifier: Intended Audience :: Information Technology
Classifier: Topic :: Scientific/Engineering :: Artificial Intelligence
Classifier: Topic :: Scientific/Engineering
Classifier: Topic :: Text Processing
Classifier: License :: OSI Approved :: GNU General Public License v3 (GPLv3)
Classifier: Programming Language :: Python :: 3 :: Only
Requires-Python: >=3.2
Requires-Dist: numpy
Requires-Dist: scipy
Requires-Dist: Cython
Requires-Dist: progressbar
Requires-Dist: choldate
